frameon/__init__.py
frameon/api/__init__.py
frameon/api/utils.py
frameon/core/__init__.py
frameon/core/base.py
frameon/dataframe/__init__.py
frameon/dataframe/analysis/__init__.py
frameon/dataframe/analysis/cohort.py
frameon/dataframe/analysis/correlation.py
frameon/dataframe/analysis/rfm.py
frameon/dataframe/analysis/segment_analysis.py
frameon/dataframe/analysis/text_analysis.py
frameon/dataframe/explore/__init__.py
frameon/dataframe/explore/anomalies.py
frameon/dataframe/explore/info.py
frameon/dataframe/preprocessing/__init__.py
frameon/dataframe/preprocessing/preprocessing.py
frameon/dataframe/statistics/__init__.py
frameon/dataframe/statistics/stat_tests.py
frameon/dataframe/visualization/__init__.py
frameon/dataframe/visualization/plot.py
frameon/datasets/__init__.py
frameon/datasets/datasets.py
frameon/datasets/diamonds.csv
frameon/datasets/iris.csv
frameon/datasets/penguins.csv
frameon/datasets/reviews.csv
frameon/datasets/superstore.csv
frameon/datasets/taxis.csv
frameon/datasets/tips.csv
frameon/datasets/titanic.csv
frameon/series/__init__.py
frameon/series/explore/__init__.py
frameon/series/explore/anomalies.py
frameon/series/explore/info.py
frameon/series/preprocessing/__init__.py
frameon/series/preprocessing/preprocessing.py
frameon/utils/__init__.py
frameon/utils/miscellaneous.py
frameon/utils/plotting/__init__.py
frameon/utils/plotting/base_bar_line_area.py
frameon/utils/plotting/base_boxplot_violin.py
frameon/utils/plotting/base_cat_compare.py
frameon/utils/plotting/base_heatmap.py
frameon/utils/plotting/base_histogram.py
frameon/utils/plotting/base_pairplot.py
frameon/utils/plotting/base_parallel_cat.py
frameon/utils/plotting/base_period_change.py
frameon/utils/plotting/base_pie_bar.py
frameon/utils/plotting/base_plot_ci.py
frameon/utils/plotting/base_qqplot.py
frameon/utils/plotting/base_wordcloud.py
frameon/utils/plotting/custom_figure.py
frameon/utils/plotting/plot_utils.py
frameon/utils/plotting/plotly_config.json
frameon-0.1.2.dist-info/LICENSE
frameon-0.1.2.dist-info/METADATA
frameon-0.1.2.dist-info/WHEEL
frameon-0.1.2.dist-info/RECORD
