Metadata-Version: 2.3
Name: frameon
Version: 0.1.2
Summary: Frameon extends pandas DataFrame with analysis methods while keeping all original functionality intact.
License: MIT
Keywords: pandas,data-analysis,data-science
Author: Pavel Grigoryev
Author-email: pavel.grigoryev.ds@gmail.com
Requires-Python: >=3.11
Classifier: License :: OSI Approved :: MIT License
Classifier: Programming Language :: Python :: 3
Classifier: Programming Language :: Python :: 3.11
Classifier: Programming Language :: Python :: 3.12
Classifier: Programming Language :: Python :: 3.13
Requires-Dist: ipython (>=9.4.0,<10.0.0)
Requires-Dist: kaleido (>=1.0.0,<2.0.0)
Requires-Dist: nltk (>=3.9.1,<4.0.0)
Requires-Dist: numpy (>=2.3.2,<3.0.0)
Requires-Dist: pandas (>=2.3.1,<3.0.0)
Requires-Dist: pingouin (>=0.5.5,<0.6.0)
Requires-Dist: plotly (>=6.2.0,<7.0.0)
Requires-Dist: rich (>=14.0.0,<15.0.0)
Requires-Dist: scikit-learn (>=1.7.1,<2.0.0)
Requires-Dist: scikit-posthocs (>=0.11.4,<0.12.0)
Requires-Dist: scipy (>=1.16.0,<2.0.0)
Requires-Dist: statsmodels (>=0.14.5,<0.15.0)
Requires-Dist: textblob (>=0.19.0,<0.20.0)
Requires-Dist: tqdm (>=4.67.1,<5.0.0)
Requires-Dist: wordcloud (>=1.9.4,<2.0.0)
Project-URL: Documentation, https://frameon.readthedocs.io/en/latest
Project-URL: Homepage, https://github.com/PavelGrigoryevDS/frameon
Project-URL: Issues, https://github.com/PavelGrigoryevDS/frameon/issues
Project-URL: Repository, https://github.com/PavelGrigoryevDS/frameon
